esel3d/__init__.py
esel3d/esel3d.py
esel3d-0.1.48.dist-info/LICENSE
esel3d-0.1.48.dist-info/METADATA
esel3d-0.1.48.dist-info/WHEEL
esel3d-0.1.48.dist-info/top_level.txt
esel3d-0.1.48.dist-info/RECORD
