Metadata-Version: 2.1
Name: esel3d
Version: 0.1.48
Summary: A 3D plotter for Google Colab and Jupyter Notebook
Home-page: https://github.com/esel-fliegen/esel3d
Author: Khan Tran
Author-email: esel.fliegen@gmail.com
License: UNKNOWN
Project-URL: Bug Tracker, https://github.com/esel-fliegen/esel3d/issues
Platform: UNKNOWN
Classifier: Programming Language :: Python :: 3
Classifier: License :: OSI Approved :: GNU General Public License (GPL)
Classifier: Operating System :: OS Independent
Requires-Python: >=3.6
License-File: LICENSE
